{
    "backend": "django",
    "db_name": "",
    "db_pass": "",
    "db_type": "sqlite",
    "db_user": "",
    "dbms": "1",
    "description": "generated product",
    "design": "soft-ui-design",
    "docker": "0",
    "err_code": 0,
    "frontend": "",
    "heroku": "0",
    "pattern": "mvc",
    "pro": "0",
    "task_id": "cb6e43f5-1dbf-4c82-8657-56a61ea087c2",
    "task_info": "Upload Sources [0%] - 326 files",
    "task_output": "cb6e43f5-1dbf-4c82-8657-56a61ea087c2.zip",
    "task_result": "SUCCESS",
    "task_state": "RUNNING",
    "task_ts_end": "2023-02-24-10-33-04",
    "task_ts_start": "2023-02-24-10-33-01"
}